README.md
setup.py
uparallel.py
uparallel.egg-info/PKG-INFO
uparallel.egg-info/SOURCES.txt
uparallel.egg-info/dependency_links.txt
uparallel.egg-info/top_level.txt