Metadata-Version: 2.1
Name: uparallel
Version: 0.1.0
Summary: uparallel - oversimplified helper for easy parallel functions execution 
Home-page: http://github.com/bobuk/uparallel
Author: Grigory Bakunov
Author-email: thebobuk@ya.ru
License: UNKNOWN
Platform: UNKNOWN
Classifier: Programming Language :: Python
Classifier: Programming Language :: Python :: 3
Classifier: Development Status :: 4 - Beta
Classifier: Environment :: Other Environment
Classifier: Intended Audience :: Developers
Classifier: Operating System :: OS Independent
Classifier: Topic :: Software Development :: Libraries :: Python Modules
